gggspider/__init__.py
gggspider-0.0.1.dist-info/LICENSE
gggspider-0.0.1.dist-info/METADATA
gggspider-0.0.1.dist-info/WHEEL
gggspider-0.0.1.dist-info/top_level.txt
gggspider-0.0.1.dist-info/RECORD
